glogformat/__init__.py
glogformat-0.1.0.dist-info/licenses/LICENSE
glogformat-0.1.0.dist-info/METADATA
glogformat-0.1.0.dist-info/WHEEL
glogformat-0.1.0.dist-info/top_level.txt
glogformat-0.1.0.dist-info/RECORD
