Metadata-Version: 2.4
Name: glogformat
Version: 0.1.0
Summary: A Python logging formatter implementing Google's glog format with microsecond precision and terminal color support.
Author-email: Aleksandar Veselinovic <aleksa@users.noreply.github.com>
License-Expression: MIT
Project-URL: Homepage, https://github.com/aleksa/glogformat
Project-URL: Documentation, https://github.com/aleksa/glogformat
Keywords: glog,logging,formatter,python,terminal,colors
Classifier: Programming Language :: Python :: 3
Classifier: Programming Language :: Python :: 3.10
Classifier: Programming Language :: Python :: 3.11
Classifier: Programming Language :: Python :: 3.12
Classifier: Programming Language :: Python :: 3.13
Classifier: Programming Language :: Python :: 3.14
Classifier: Operating System :: POSIX :: Linux
Classifier: Operating System :: MacOS
Requires-Python: >=3.10
License-File: LICENSE
Provides-Extra: test
Requires-Dist: pytest>=7.0; extra == "test"
Requires-Dist: pytest-cov>=4.0; extra == "test"
Provides-Extra: dev
Requires-Dist: black>=24.0; extra == "dev"
Requires-Dist: isort>=5.13; extra == "dev"
Requires-Dist: pylint>=3.0; extra == "dev"
Requires-Dist: mypy>=1.11; extra == "dev"
Requires-Dist: build>=1.0; extra == "dev"
Dynamic: license-file
